{
  "agent_id": "metrics",
  "agent_name": "Metrics & Analytics Agent",
  "run_id": "9c84b68d-37fe-43a3-b7b5-0c4d6eb0c06e",
  "timestamp": "2026-03-09T21:20:07.550363Z",
  "findings": [
    {
      "id": "metrics-001",
      "agent_id": "metrics",
      "type": "metric",
      "title": "North Star Metric: User Engagement Score",
      "description": "The User Engagement Score is defined as a composite metric reflecting user interaction with the platform, including content consumption and session duration. It serves as the primary measure of overall user engagement and satisfaction.",
      "impact": "critical",
      "confidence": "validated",
      "assumptions": [
        "User engagement is a strong predictor of retention and monetization."
      ],
      "evidence": [
        {
          "source_id": "DOC-004",
          "source_type": "doc",
          "excerpt": "engagement_score: 6.2",
          "url": null
        }
      ],
      "recommendations": [
        "Monitor engagement score trends weekly to identify areas for improvement."
      ],
      "tags": [
        "north_star"
      ],
      "metadata": {
        "baseline": 6.2,
        "target": 7.5,
        "measurement_method": "calculated from user interaction data"
      }
    },
    {
      "id": "metrics-002",
      "agent_id": "metrics",
      "type": "metric",
      "title": "Primary KPI: Content Click-Through Rate (CTR)",
      "description": "The Content CTR measures the percentage of users who click on recommended content. It is a key indicator of the effectiveness of the recommendation engine.",
      "impact": "high",
      "confidence": "validated",
      "assumptions": [
        "Higher CTR indicates better content relevance and user satisfaction."
      ],
      "evidence": [
        {
          "source_id": "DOC-004",
          "source_type": "doc",
          "excerpt": "content_ctr: 0.15",
          "url": null
        }
      ],
      "recommendations": [
        "Aim for a 20% improvement in CTR within the next 60 days."
      ],
      "tags": [
        "input_metric"
      ],
      "metadata": {
        "baseline": 0.15,
        "target": 0.18,
        "measurement_method": "calculated from user click data"
      }
    },
    {
      "id": "metrics-003",
      "agent_id": "metrics",
      "type": "metric",
      "title": "Guardrail Metric: Privacy Opt-Out Rate",
      "description": "The Privacy Opt-Out Rate indicates the percentage of users opting out of data collection. This metric must not increase significantly as it reflects user trust and compliance with privacy regulations.",
      "impact": "high",
      "confidence": "validated",
      "assumptions": [
        "A lower opt-out rate indicates better user trust in the platform."
      ],
      "evidence": [
        {
          "source_id": "DOC-004",
          "source_type": "doc",
          "excerpt": "privacy_opt_out_rate: 0.22",
          "url": null
        }
      ],
      "recommendations": [
        "Implement user education initiatives to reduce opt-out rates."
      ],
      "tags": [
        "guardrail"
      ],
      "metadata": {
        "baseline": 0.22,
        "target": 0.2,
        "measurement_method": "calculated from user preference data"
      }
    },
    {
      "id": "metrics-004",
      "agent_id": "metrics",
      "type": "gap",
      "title": "Instrumentation Gap: User Behavior Tracking",
      "description": "There is currently no comprehensive tracking of user behavior metrics such as browsing history, click patterns, and scroll depth. This gap limits the ability to analyze user engagement effectively.",
      "impact": "high",
      "confidence": "directional",
      "assumptions": [
        "Comprehensive tracking will provide insights into user preferences and behavior."
      ],
      "evidence": [
        {
          "source_id": "PROF-101",
          "source_type": "ticket",
          "excerpt": "Implement a data ingestion pipeline that captures browsing history, click patterns, scroll depth, and time-on-page metrics.",
          "url": null
        }
      ],
      "recommendations": [
        "Develop and implement a user behavior tracking pipeline as outlined in PROF-101."
      ],
      "tags": [],
      "metadata": {}
    },
    {
      "id": "metrics-005",
      "agent_id": "metrics",
      "type": "recommendation",
      "title": "Experiment Opportunity: Content Recommendation Engine",
      "description": "Conduct A/B testing on the new recommendation engine to measure its impact on content CTR. Set statistical parameters to ensure a minimum detectable effect size of 5% with a confidence level of 95%.",
      "impact": "high",
      "confidence": "directional",
      "assumptions": [
        "A/B testing will provide clear insights into the effectiveness of the new recommendation engine."
      ],
      "evidence": [
        {
          "source_id": "PROF-102",
          "source_type": "ticket",
          "excerpt": "Target: 20% improvement in content CTR within 60 days.",
          "url": null
        }
      ],
      "recommendations": [
        "Design A/B tests with appropriate sample sizes to validate the recommendation engine's effectiveness."
      ],
      "tags": [],
      "metadata": {
        "baseline": 0.15,
        "target": 0.18,
        "measurement_method": "A/B testing"
      }
    }
  ],
  "summary": "The analysis identifies key metrics for the PersonaLens product, including a North Star metric focused on user engagement, primary KPIs for content CTR, and guardrails for privacy opt-out rates. Gaps in user behavior tracking and opportunities for experimentation with the recommendation engine are also highlighted.",
  "errors": []
}